[
    {
        "key": "dbln",
        "value": "%7B%2261572236771681%22%3A%22IGeu4kJw%22%2C%22100063957348999%22%3A%22DABKvGLr%22%2C%2261565846734405%22%3A%22nUZO6Y6b%22%2C%22100053744656021%22%3A%22AWYfqXSZ%22%7D",
        "domain": "facebook.com",
        "path": "/login/device-based/",
        "hostOnly": false,
        "creation": "2025-08-16T16:49:24.634Z",
        "lastAccessed": "2025-08-16T16:49:24.634Z"
    },
    {
        "key": "datr",
        "value": "sZyFaLZDR4uY0vRtku2jM5Tb",
        "domain": "facebook.com",
        "path": "/",
        "hostOnly": false,
        "creation": "2025-08-16T16:49:24.634Z",
        "lastAccessed": "2025-08-16T16:49:24.634Z"
    },
    {
        "key": "sb",
        "value": "sZyFaGVivv0BKuGdBbdIZDwA",
        "domain": "facebook.com",
        "path": "/",
        "hostOnly": false,
        "creation": "2025-08-16T16:49:24.634Z",
        "lastAccessed": "2025-08-16T16:49:24.634Z"
    },
    {
        "key": "ps_l",
        "value": "1",
        "domain": "facebook.com",
        "path": "/",
        "hostOnly": false,
        "creation": "2025-08-16T16:49:24.634Z",
        "lastAccessed": "2025-08-16T16:49:24.634Z"
    },
    {
        "key": "ps_n",
        "value": "1",
        "domain": "facebook.com",
        "path": "/",
        "hostOnly": false,
        "creation": "2025-08-16T16:49:24.634Z",
        "lastAccessed": "2025-08-16T16:49:24.634Z"
    },
    {
        "key": "pas",
        "value": "61572236771681%3AdnDah7wn8g%2C100063957348999%3AUVzSIvEWSB%2C61565846734405%3A94Q0SFdnSy%2C100053744656021%3AJd77RSUHY2",
        "domain": "facebook.com",
        "path": "/",
        "hostOnly": false,
        "creation": "2025-08-16T16:49:24.634Z",
        "lastAccessed": "2025-08-16T16:49:24.634Z"
    },
    {
        "key": "dpr",
        "value": "2",
        "domain": "facebook.com",
        "path": "/",
        "hostOnly": false,
        "creation": "2025-08-16T16:49:24.634Z",
        "lastAccessed": "2025-08-16T16:49:24.634Z"
    },
    {
        "key": "vpd",
        "value": "v1%3B566x360x2",
        "domain": "facebook.com",
        "path": "/",
        "hostOnly": false,
        "creation": "2025-08-16T16:49:24.634Z",
        "lastAccessed": "2025-08-16T16:49:24.634Z"
    },
    {
        "key": "m_pixel_ratio",
        "value": "2",
        "domain": "facebook.com",
        "path": "/",
        "hostOnly": false,
        "creation": "2025-08-16T16:49:24.634Z",
        "lastAccessed": "2025-08-16T16:49:24.634Z"
    },
    {
        "key": "wd",
        "value": "360x640",
        "domain": "facebook.com",
        "path": "/",
        "hostOnly": false,
        "creation": "2025-08-16T16:49:24.634Z",
        "lastAccessed": "2025-08-16T16:49:24.634Z"
    },
    {
        "key": "c_user",
        "value": "61565846734405",
        "domain": "facebook.com",
        "path": "/",
        "hostOnly": false,
        "creation": "2025-08-16T16:49:24.634Z",
        "lastAccessed": "2025-08-16T16:49:24.634Z"
    },
    {
        "key": "xs",
        "value": "10%3Are5roVi8uTvWbQ%3A2%3A1755362999%3A-1%3A-1",
        "domain": "facebook.com",
        "path": "/",
        "hostOnly": false,
        "creation": "2025-08-16T16:49:24.634Z",
        "lastAccessed": "2025-08-16T16:49:24.634Z"
    },
    {
        "key": "fr",
        "value": "0iJstPbisj2sxEsma.AWdDfEWdn64-lvqosaMnlZGNBoX4l0bTe_1jAajx2nNU_nTqLWo.BohZyx..AAA.0.0.BooLa7.AWe91_saLO66bVGQdxNEeKnAfsk",
        "domain": "facebook.com",
        "path": "/",
        "hostOnly": false,
        "creation": "2025-08-16T16:49:24.634Z",
        "lastAccessed": "2025-08-16T16:49:24.634Z"
    },
    {
        "key": "locale",
        "value": "en_GB",
        "domain": "facebook.com",
        "path": "/",
        "hostOnly": false,
        "creation": "2025-08-16T16:49:24.634Z",
        "lastAccessed": "2025-08-16T16:49:24.635Z"
    },
    {
        "key": "fbl_st",
        "value": "100435400%3BT%3A29256049",
        "domain": "facebook.com",
        "path": "/",
        "hostOnly": false,
        "creation": "2025-08-16T16:49:24.635Z",
        "lastAccessed": "2025-08-16T16:49:24.635Z"
    },
    {
        "key": "wl_cbv",
        "value": "v2%3Bclient_version%3A2894%3Btimestamp%3A1755363003",
        "domain": "facebook.com",
        "path": "/",
        "hostOnly": false,
        "creation": "2025-08-16T16:49:24.635Z",
        "lastAccessed": "2025-08-16T16:49:24.635Z"
    }
]
